weather_app/__init__.py
weather_app/api.py
weather_app/app.py
weather_app/render.py
weather_app_simon-0.0.2.dist-info/LICENSE
weather_app_simon-0.0.2.dist-info/METADATA
weather_app_simon-0.0.2.dist-info/WHEEL
weather_app_simon-0.0.2.dist-info/entry_points.txt
weather_app_simon-0.0.2.dist-info/top_level.txt
weather_app_simon-0.0.2.dist-info/RECORD
